versctrl.py
versctrl-1.0.3.dist-info/licenses/LICENSE
versctrl-1.0.3.dist-info/METADATA
versctrl-1.0.3.dist-info/WHEEL
versctrl-1.0.3.dist-info/entry_points.txt
versctrl-1.0.3.dist-info/top_level.txt
versctrl-1.0.3.dist-info/RECORD
