Metadata-Version: 2.4
Name: versctrl
Version: 1.0.3
Summary: Lightweight version control CLI tool with smart file detection and PyQt6 GUI
Home-page: https://github.com/v7ren/verctrl
Author: REN
Author-email: REN <totallynotbedlessnoob@gmail.com>
License: MIT
Project-URL: Homepage, https://github.com/v7ren/verctrl
Project-URL: Repository, https://github.com/v7ren/verctrl
Project-URL: Issues, https://github.com/v7ren/verctrl/issues
Keywords: version-control,backup,cli,gui,pyqt6
Classifier: Development Status :: 4 - Beta
Classifier: Intended Audience :: Developers
Classifier: Topic :: Software Development :: Version Control
Classifier: License :: OSI Approved :: MIT License
Classifier: Programming Language :: Python :: 3
Requires-Python: >=3.7
License-File: LICENSE
Requires-Dist: PyQt6>=6.0.0
Requires-Dist: lucide-py>=0.1.0
Dynamic: author
Dynamic: home-page
Dynamic: license-file
Dynamic: requires-python
